{
    "slug": "rephood",
    "title": "RepHood — Autonomous Agentic Reputation on Robinhood Chain",
    "tagline": "Institutional-grade reputation analytics using specialized AI agents to emit real-time, verifiable on-chain attestations",
    "description": "RepHood is a premium reputation analytics platform built on the Robinhood Chain (Arbitrum Orbit Stack) and powered by Virtuals Protocol. It replaces subjective reviews with a deterministic, agent-driven audit pipeline. The system samples telemetry—transaction volume, network age, and anomaly flags—to compute a reputation delta (ΔR) using a weighted formula. Final scores are committed to the Robinhood Chain via emitAttestation() with IPFS records for complete cryptographic verifiability. Built with Next.js 16, Wagmi v2, and Tailwind v4.",
    "status": "Live MVP on Robinhood Chain",
    "topic": "ai-agents",
    "topics": [
        "robinhood-chain",
        "virtuals",
        "reputation-engine",
        "attestation",
        "arbitrum-orbit",
        "wagmi"
    ],
    "hidden": false,
    "builder": {
        "name": "RepHood Team",
        "url": "https://rephood.vercel.app"
    },
    "links": {
        "repo": "https://github.com/Anmol-345/rephood",
        "demo": "https://rephood.vercel.app",
        "share": "https://github.com/Anmol-345/rephood",
        "feedback": "https://github.com/Anmol-345/rephood/issues"
    },
    "primitives": [
        "wallet",
        "agent"
    ],
    "visual": {
        "kind": "Institutional agentic reputation dashboard + Web3 wallet connection",
        "eyebrow": "ai-agents · virtuals · robinhood chain",
        "title": "deterministic agent trust & telemetry"
    },
    "skills": [],
    "artifacts": [
        {
            "label": "Live RepHood Web App",
            "href": "https://rephood.vercel.app",
            "kind": "demo"
        },
        {
            "label": "GitHub Source Repository",
            "href": "https://github.com/Anmol-345/rephood",
            "kind": "repo"
        },
        {
            "label": "Virtuals V2 SDK Script (Privy Auth)",
            "href": "https://github.com/Anmol-345/rephood/blob/main/scripts/register-agent.ts",
            "kind": "repo"
        },
        {
            "label": "Robinhood Chain Smart Contract",
            "href": "https://github.com/Anmol-345/rephood/blob/main/contracts/RepHoodAttestation.sol",
            "kind": "repo"
        }
    ],
    "feedbackPrompts": [
        "Which additional telemetry vectors should RepHood sample from the Robinhood Chain?",
        "Should the emitAttestation() parameters be natively integrated into Virtuals Protocol governance?",
        "What features would best enhance the Live Pipeline Audit Station console?"
    ]
}